LICENSE
MANIFEST.in
README.md
setup.cfg
setup.py
digitalocean_python.egg-info/PKG-INFO
digitalocean_python.egg-info/SOURCES.txt
digitalocean_python.egg-info/dependency_links.txt
digitalocean_python.egg-info/requires.txt
digitalocean_python.egg-info/top_level.txt
pyocean/__init__.py
pyocean/action.py
pyocean/base.py
pyocean/domain.py
pyocean/domainrecord.py
pyocean/droplet.py
pyocean/exceptions.py
pyocean/image.py
pyocean/key.py
pyocean/region.py
pyocean/size.py