Metadata-Version: 1.0
Name: digitalocean-python
Version: 0.1.5
Summary: Python wrapper for the DigitalOcean API v2
Home-page: https://github.com/bsdnoobz/pyocean
Author: Nashruddin Amin
Author-email: nashruddin.amin@gmail.com
License: MIT
Keywords: digitalocean api python
Platform: UNKNOWN
